emtvlcapi/__init__.py
emtvlcapi/__main__.py
emtvlcapi/emtvlcapi.py
emtvlcapi-1.0.0.dist-info/LICENSE
emtvlcapi-1.0.0.dist-info/METADATA
emtvlcapi-1.0.0.dist-info/WHEEL
emtvlcapi-1.0.0.dist-info/top_level.txt
emtvlcapi-1.0.0.dist-info/RECORD
