Metadata-Version: 2.1
Name: emtvlcapi
Version: 1.0.0
Summary: Python module that retrieves bus times for a given stop or stops within an extent for EMT Valencia
Author-email: Ed0 <ed0@ed0.es>
License: GNU GENERAL PUBLIC LICENSE
Project-URL: Homepage, https://github.com/ElEd0/EMTValencia-API
Project-URL: Issues, https://github.com/ElEd0/EMTValencia-API/issues
Keywords: emt,vlc,valencia,api,parada,stop,bus,time,tiempo
Classifier: License :: OSI Approved :: GNU General Public License v3 or later (GPLv3+)
Classifier: Programming Language :: Python
Classifier: Programming Language :: Python :: 3
Requires-Python: >=3.6
License-File: LICENSE
Requires-Dist: requests
